databird_drivers/climate/__init__.py
databird_drivers/climate/c3s.py
databird_drivers/climate/earthdata.py
databird_drivers/climate/ecmwf.py
databird_driver_climate-0.1.2.dist-info/METADATA
databird_driver_climate-0.1.2.dist-info/WHEEL
databird_driver_climate-0.1.2.dist-info/top_level.txt
databird_driver_climate-0.1.2.dist-info/RECORD
