Metadata-Version: 2.1
Name: databird-driver-climate
Version: 0.1.2
Summary: Data sources for climate and atmospheric research.
Home-page: https://github.com/jonas-hagen/databird-driver-climate
Author: Jonas Hagen
Author-email: jonas.hagen@iap.unibe.ch
Maintainer: Jonas Hagen
Maintainer-email: jonas.hagen@iap.unibe.ch
License: MIT
Platform: UNKNOWN
Classifier: Operating System :: OS Independent
Requires-Python: >=3.5.*, <4
Requires-Dist: cdsapi
Requires-Dist: databird
Requires-Dist: ecmwf-api-client
Requires-Dist: lxml
Requires-Dist: netcdf4
Requires-Dist: pydap
Requires-Dist: xarray
